{"Menu": {"Trưa": [{"name": "Cơm trắng gạo bắc hương", "weight": 0.6, "thanhPhanMonAn": [{"name": "Gạo Bắc Hương", "dinhLuongGoc": 70.0, "donGiaGoc": 1295.0, "trongSo": 1.0867794913586777, "dinhLuongDieuChinh": 76.07456439510744, "donGiaDieuChinh": 1473.922229258822}]}, {"name": "Thịt lợn, gà om nấm", "weight": 0.2, "thanhPhanMonAn": [{"name": "Hành lá", "dinhLuongGoc": 5.0, "donGiaGoc": 1260.0, "trongSo": 1.6110561464198745, "dinhLuongDieuChinh": 8.055280732099373, "donGiaDieuChinh": 1260.0}, {"name": "Nấm hương khô", "dinhLuongGoc": 10.0, "donGiaGoc": 18550.0, "trongSo": 1.6110561464198745, "dinhLuongDieuChinh": 16.110561464198746, "donGiaDieuChinh": 18550.0}, {"name": "Dầu thực vật", "dinhLuongGoc": 2.0, "donGiaGoc": 4270.0, "trongSo": 1.6110561464198745, "dinhLuongDieuChinh": 3.222112292839749, "donGiaDieuChinh": 4270.0}, {"name": "Gia vị", "dinhLuongGoc": 0.4, "donGiaGoc": 8750.0, "trongSo": 1.6110561464198745, "dinhLuongDieuChinh": 0.6444224585679499, "donGiaDieuChinh": 8750.0}, {"name": "Thịt lợn, nạc vai", "dinhLuongGoc": 20.0, "donGiaGoc": 9566.66666666667, "trongSo": 1.6110561464198745, "dinhLuongDieuChinh": 32.22112292839749, "donGiaDieuChinh": 9566.66666666667}, {"name": "Thịt gà công nghiệp, đùi(VDD)", "dinhLuongGoc": 25.0, "donGiaGoc": 7700.0, "trongSo": 1.6110561464198745, "dinhLuongDieuChinh": 40.27640366049686, "donGiaDieuChinh": 7700.0}]}, {"name": "Cải thảo xào", "weight": 0.2, "thanhPhanMonAn": [{"name": "Dầu thực vật", "dinhLuongGoc": 4.0, "donGiaGoc": 4270.0, "trongSo": 2.1936420846921623, "dinhLuongDieuChinh": 8.774568338768649, "donGiaDieuChinh": 4270.0}, {"name": "Gia vị", "dinhLuongGoc": 0.4, "donGiaGoc": 8750.0, "trongSo": 2.1936420846921623, "dinhLuongDieuChinh": 0.8774568338768649, "donGiaDieuChinh": 8750.0}, {"name": "Cải thảo", "dinhLuongGoc": 30.0, "donGiaGoc": 1750.0, "trongSo": 2.1936420846921623, "dinhLuongDieuChinh": 65.80926254076486, "donGiaDieuChinh": 1750.0}]}], "Chiều": [{"name": "Phở bò hành mùi", "weight": 1, "thanhPhanMonAn": [{"name": "Bánh phở", "dinhLuongGoc": 60.0, "donGiaGoc": 3500.0, "trongSo": 1.2979630062334575, "dinhLuongDieuChinh": 77.87778037400744, "donGiaDieuChinh": 3500.0}, {"name": "Hành lá", "dinhLuongGoc": 5.0, "donGiaGoc": 1260.0, "trongSo": 1.2979630062334575, "dinhLuongDieuChinh": 6.4898150311672875, "donGiaDieuChinh": 1260.0}, {"name": "Rau mùi", "dinhLuongGoc": 3.0, "donGiaGoc": 2800.0, "trongSo": 1.2979630062334575, "dinhLuongDieuChinh": 3.8938890187003725, "donGiaDieuChinh": 2800.0}, {"name": "Dầu thực vật", "dinhLuongGoc": 4.0, "donGiaGoc": 4270.0, "trongSo": 1.2979630062334575, "dinhLuongDieuChinh": 5.19185202493383, "donGiaDieuChinh": 4270.0}, {"name": "Thịt bò loại I", "dinhLuongGoc": 20.0, "donGiaGoc": 17500.0, "trongSo": 1.2979630062334575, "dinhLuongDieuChinh": 25.95926012466915, "donGiaDieuChinh": 17500.0}, {"name": "Gia vị", "dinhLuongGoc": 0.4, "donGiaGoc": 8750.0, "trongSo": 1.2979630062334575, "dinhLuongDieuChinh": 0.5191852024933831, "donGiaDieuChinh": 8750.0}]}], "Phụ chiều": [{"name": "Chè khoai môn nước cốt dừa", "weight": 1, "thanhPhanMonAn": [{"name": "Khoai môn", "dinhLuongGoc": 40.0, "donGiaGoc": 1680.0, "trongSo": 0.627958715465687, "dinhLuongDieuChinh": 25.118348618627483, "donGiaDieuChinh": 1680.0}, {"name": "Đường kính", "dinhLuongGoc": 10.0, "donGiaGoc": 1750.0, "trongSo": 0.627958715465687, "dinhLuongDieuChinh": 6.279587154656871, "donGiaDieuChinh": 1750.0}, {"name": "Nước cốt dừa", "dinhLuongGoc": 10.0, "donGiaGoc": 8750.0, "trongSo": 0.627958715465687, "dinhLuongDieuChinh": 6.279587154656871, "donGiaDieuChinh": 8750.0}]}]}, "type": 1, "result": ["Thành tiền: 21000.0 (OK)"],     "response": 200,
    "giaTien": 30000,
    "soBua": 3}