{"Menu": {"Trưa": [{"name": "Cơm trộn Hàn Quốc", "weight": 0.6, "thanhPhanMonAn": [{"name": "Gạo tẻ máy", "dinhLuongGoc": 80.0, "donGiaGoc": 770.0, "trongSo": 1.0, "dinhLuongDieuChinh": 80.0, "donGiaDieuChinh": 616.0}, {"name": "Cải ngọt", "dinhLuongGoc": 20.0, "donGiaGoc": 630.0, "trongSo": 1.0, "dinhLuongDieuChinh": 20.0, "donGiaDieuChinh": 504.0}]}, {"name": "Thịt bò sốt nấm", "weight": 0.2, "thanhPhanMonAn": [{"name": "Hành lá", "dinhLuongGoc": 5.0, "donGiaGoc": 1260.0, "trongSo": 1.6050841196065613, "dinhLuongDieuChinh": 8.025420598032806, "donGiaDieuChinh": 1008.0}, {"name": "Nấm hương khô", "dinhLuongGoc": 5.0, "donGiaGoc": 18550.0, "trongSo": 1.6050841196065613, "dinhLuongDieuChinh": 8.025420598032806, "donGiaDieuChinh": 14840.0}, {"name": "Dầu thực vật", "dinhLuongGoc": 3.0, "donGiaGoc": 4270.0, "trongSo": 1.6050841196065613, "dinhLuongDieuChinh": 4.815252358819684, "donGiaDieuChinh": 3416.0}, {"name": "Thịt bò loại I", "dinhLuongGoc": 30.0, "donGiaGoc": 17500.0, "trongSo": 1.6050841196065613, "dinhLuongDieuChinh": 48.152523588196836, "donGiaDieuChinh": 15121.038806648343}, {"name": "Gia vị", "dinhLuongGoc": 0.4, "donGiaGoc": 8750.0, "trongSo": 1.6050841196065613, "dinhLuongDieuChinh": 0.6420336478426245, "donGiaDieuChinh": 8750.0}]}, {"name": "Canh cải nấu thịt băm", "weight": 0.2, "thanhPhanMonAn": [{"name": "Cải xanh", "dinhLuongGoc": 40.0, "donGiaGoc": 1750.0, "trongSo": 2.429418399676747, "dinhLuongDieuChinh": 97.17673598706988, "donGiaDieuChinh": 1750.0}, {"name": "Dầu thực vật", "dinhLuongGoc": 2.0, "donGiaGoc": 4270.0, "trongSo": 2.429418399676747, "dinhLuongDieuChinh": 4.858836799353494, "donGiaDieuChinh": 4270.0}, {"name": "Gia vị", "dinhLuongGoc": 0.4, "donGiaGoc": 8750.0, "trongSo": 2.429418399676747, "dinhLuongDieuChinh": 0.9717673598706988, "donGiaDieuChinh": 8750.0}, {"name": "Thịt lợn, nạc vai", "dinhLuongGoc": 20.0, "donGiaGoc": 9566.66666666667, "trongSo": 2.429418399676747, "dinhLuongDieuChinh": 48.58836799353494, "donGiaDieuChinh": 9566.66666666667}]}], "Chiều": [{"name": "Cháo cá trắm rau cải", "weight": 1, "thanhPhanMonAn": [{"name": "Gạo nếp cái", "dinhLuongGoc": 5.0, "donGiaGoc": 2800.0, "trongSo": 0.8012451390581241, "dinhLuongDieuChinh": 4.00622569529062, "donGiaDieuChinh": 2800.0}, {"name": "Gạo tẻ máy", "dinhLuongGoc": 35.0, "donGiaGoc": 770.0, "trongSo": 0.8012451390581241, "dinhLuongDieuChinh": 28.043579867034342, "donGiaDieuChinh": 770.0}, {"name": "Cải xanh", "dinhLuongGoc": 30.0, "donGiaGoc": 1750.0, "trongSo": 0.8012451390581241, "dinhLuongDieuChinh": 24.037354171743722, "donGiaDieuChinh": 1750.0}, {"name": "Dầu thực vật", "dinhLuongGoc": 4.0, "donGiaGoc": 4270.0, "trongSo": 0.8012451390581241, "dinhLuongDieuChinh": 3.2049805562324964, "donGiaDieuChinh": 4270.0}, {"name": "Cá trắm cỏ", "dinhLuongGoc": 50.0, "donGiaGoc": 5600.0, "trongSo": 0.8012451390581241, "dinhLuongDieuChinh": 40.0622569529062, "donGiaDieuChinh": 5600.0}, {"name": "Gia vị", "dinhLuongGoc": 2.0, "donGiaGoc": 8750.0, "trongSo": 0.8012451390581241, "dinhLuongDieuChinh": 1.6024902781162482, "donGiaDieuChinh": 8750.0}]}], "Phụ chiều": [{"name": "Chè khoai môn nước cốt dừa", "weight": 1, "thanhPhanMonAn": [{"name": "Khoai môn", "dinhLuongGoc": 40.0, "donGiaGoc": 1680.0, "trongSo": 1.0, "dinhLuongDieuChinh": 40.0, "donGiaDieuChinh": 1680.0}, {"name": "Đường kính", "dinhLuongGoc": 10.0, "donGiaGoc": 1750.0, "trongSo": 1.0, "dinhLuongDieuChinh": 10.0, "donGiaDieuChinh": 1750.0}, {"name": "Nước cốt dừa", "dinhLuongGoc": 10.0, "donGiaGoc": 8750.0, "trongSo": 1.0, "dinhLuongDieuChinh": 10.0, "donGiaDieuChinh": 8750.0}]}]}, "type": 1, "result": ["Thành tiền: 21000.0 (OK)"],     "response": 200,
    "giaTien": 30000,
    "soBua": 3}