{"Menu": {"Sáng": [{"name": "Bún bò rau mồng tơi", "weight": 1, "thanhPhanMonAn": [{"name": "Rau mồng tơi", "dinhLuongGoc": 40.0, "donGiaGoc": 2310.0, "trongSo": 0.419708739792585, "dinhLuongDieuChinh": 16.7883495917034, "donGiaDieuChinh": 1848.0}, {"name": "Dầu thực vật", "dinhLuongGoc": 4.0, "donGiaGoc": 4270.0, "trongSo": 0.3000770080943897, "dinhLuongDieuChinh": 1.2003080323775588, "donGiaDieuChinh": 3416.0}, {"name": "Thịt bò loại I", "dinhLuongGoc": 25.0, "donGiaGoc": 17500.0, "trongSo": 0.6430458712151015, "dinhLuongDieuChinh": 16.076146780377538, "donGiaDieuChinh": 14000.0}, {"name": "Gia vị", "dinhLuongGoc": 2.0, "donGiaGoc": 8750.0, "trongSo": 0.4678622079089727, "dinhLuongDieuChinh": 0.9357244158179454, "donGiaDieuChinh": 7000.0}, {"name": "Bún khô", "dinhLuongGoc": 50.0, "donGiaGoc": 7700.0, "trongSo": 0.2754313905394685, "dinhLuongDieuChinh": 13.771569526973426, "donGiaDieuChinh": 6160.0}]}], "Phụ sáng": [{"name": "Sữa chua TH True Milk", "weight": 1, "thanhPhanMonAn": [{"name": "Sữa chua TH True Milk", "dinhLuongGoc": 100.0, "donGiaGoc": 3111.11111111111, "trongSo": 0.5918877541593841, "dinhLuongDieuChinh": 59.18877541593841, "donGiaDieuChinh": 2488.888888888888}]}], "Trưa": [{"name": "Cơm trắng", "weight": 0.6, "thanhPhanMonAn": [{"name": "Gạo tẻ máy", "dinhLuongGoc": 80.0, "donGiaGoc": 770.0, "trongSo": 0.7984556137415808, "dinhLuongDieuChinh": 63.876449099326464, "donGiaDieuChinh": 616.0}]}, {"name": "Thịt kho củ cải", "weight": 0.2, "thanhPhanMonAn": [{"name": "Củ cải trắng", "dinhLuongGoc": 20.0, "donGiaGoc": 2100.0, "trongSo": 1.1861368937637529, "dinhLuongDieuChinh": 23.722737875275058, "donGiaDieuChinh": 1680.0}, {"name": "Dầu thực vật", "dinhLuongGoc": 4.0, "donGiaGoc": 4270.0, "trongSo": 1.04962148443708, "dinhLuongDieuChinh": 4.19848593774832, "donGiaDieuChinh": 3416.0}, {"name": "Gia vị", "dinhLuongGoc": 2.0, "donGiaGoc": 8750.0, "trongSo": 1.4158408934412678, "dinhLuongDieuChinh": 2.8316817868825357, "donGiaDieuChinh": 7000.0}, {"name": "Nước cốt dừa", "dinhLuongGoc": 5.0, "donGiaGoc": 8750.0, "trongSo": 1.2444506629618377, "dinhLuongDieuChinh": 6.222253314809189, "donGiaDieuChinh": 7767.958885874485}, {"name": "Thịt lợn, nạc vai", "dinhLuongGoc": 30.0, "donGiaGoc": 9566.66666666667, "trongSo": 1.4094304024422861, "dinhLuongDieuChinh": 42.282912073268584, "donGiaDieuChinh": 9566.66666666667}]}, {"name": "Canh rau mông tơi nấu hến", "weight": 0.2, "thanhPhanMonAn": [{"name": "Rau mồng tơi", "dinhLuongGoc": 30.0, "donGiaGoc": 2310.0, "trongSo": 1.4281919140927002, "dinhLuongDieuChinh": 42.845757422781006, "donGiaDieuChinh": 2310.0}, {"name": "Dầu thực vật", "dinhLuongGoc": 5.0, "donGiaGoc": 4270.0, "trongSo": 1.3409901626097205, "dinhLuongDieuChinh": 6.704950813048603, "donGiaDieuChinh": 4270.0}, {"name": "Hến", "dinhLuongGoc": 20.0, "donGiaGoc": 6650.0, "trongSo": 1.246302038244909, "dinhLuongDieuChinh": 24.926040764898183, "donGiaDieuChinh": 6650.0}, {"name": "Đường kính", "dinhLuongGoc": 2.0, "donGiaGoc": 1750.0, "trongSo": 1.3409901626097205, "dinhLuongDieuChinh": 2.681980325219441, "donGiaDieuChinh": 1750.0}, {"name": "Nước mắm loại I", "dinhLuongGoc": 2.0, "donGiaGoc": 4666.66666666667, "trongSo": 1.3409901626097205, "dinhLuongDieuChinh": 2.681980325219441, "donGiaDieuChinh": 4666.66666666667}, {"name": "Hạt nêm Aji-ngon", "dinhLuongGoc": 2.0, "donGiaGoc": 7000.0, "trongSo": 1.2097156310610009, "dinhLuongDieuChinh": 2.4194312621220018, "donGiaDieuChinh": 7000.0}]}], "Chiều": [{"name": "Cháo lươn củ dền", "weight": 1, "thanhPhanMonAn": [{"name": "Gạo nếp cái", "dinhLuongGoc": 5.0, "donGiaGoc": 2800.0, "trongSo": 0.6874846925354463, "dinhLuongDieuChinh": 3.4374234626772315, "donGiaDieuChinh": 2800.0}, {"name": "Gạo tẻ máy", "dinhLuongGoc": 40.0, "donGiaGoc": 770.0, "trongSo": 0.6874846925354463, "dinhLuongDieuChinh": 27.499387701417852, "donGiaDieuChinh": 770.0}, {"name": "Dầu thực vật", "dinhLuongGoc": 3.0, "donGiaGoc": 4270.0, "trongSo": 0.5234916459883601, "dinhLuongDieuChinh": 1.5704749379650802, "donGiaDieuChinh": 4270.0}, {"name": "Lươn", "dinhLuongGoc": 20.0, "donGiaGoc": 14000.0, "trongSo": 0.8349628275750536, "dinhLuongDieuChinh": 16.699256551501072, "donGiaDieuChinh": 14000.0}, {"name": "Gia vị", "dinhLuongGoc": 3.0, "donGiaGoc": 8750.0, "trongSo": 0.7945815858869631, "dinhLuongDieuChinh": 2.3837447576608897, "donGiaDieuChinh": 8750.0}, {"name": "Củ dền", "dinhLuongGoc": 30.0, "donGiaGoc": 980.0, "trongSo": 0.6874846925354463, "dinhLuongDieuChinh": 20.62454077606339, "donGiaDieuChinh": 980.0}]}], "Phụ chiều": [{"name": "Ngũ cốc trộn sữa", "weight": 1, "thanhPhanMonAn": [{"name": "Sữa tươi Vinamilk", "dinhLuongGoc": 80.0, "donGiaGoc": 2450.0, "trongSo": 0.5059945455174822, "dinhLuongDieuChinh": 40.47956364139858, "donGiaDieuChinh": 2450.0}, {"name": "Ngũ cốc Kellogg's Frostise", "dinhLuongGoc": 20.0, "donGiaGoc": 29235.2941176471, "trongSo": 0.5059945455174822, "dinhLuongDieuChinh": 10.119890910349644, "donGiaDieuChinh": 29235.2941176471}]}]}, "type": 1, "result": ["Thành tiền: 21000.0 (OK)"],     "response": 200,
    "giaTien": 30000,
    "soBua": 5}