{"Menu": {"Sáng": [{"name": "Súp tôm bí đỏ", "weight": 1, "thanhPhanMonAn": [{"name": "Bí ngô", "dinhLuongGoc": 25.0, "donGiaGoc": 2800.0, "trongSo": 0.8253876467076572, "dinhLuongDieuChinh": 20.63469116769143, "donGiaDieuChinh": 2240.0}, {"name": "Dầu thực vật", "dinhLuongGoc": 2.0, "donGiaGoc": 4270.0, "trongSo": 0.667552212897422, "dinhLuongDieuChinh": 1.335104425794844, "donGiaDieuChinh": 3416.0}, {"name": "Tôm lớp", "dinhLuongGoc": 30.0, "donGiaGoc": 12600.0, "trongSo": 0.7034965434900919, "dinhLuongDieuChinh": 21.10489630470276, "donGiaDieuChinh": 10080.0}, {"name": "Gia vị", "dinhLuongGoc": 0.4, "donGiaGoc": 8750.0, "trongSo": 0.931068586561161, "dinhLuongDieuChinh": 0.3724274346244644, "donGiaDieuChinh": 7000.0}, {"name": "Bột ngô + bột năng", "dinhLuongGoc": 15.0, "donGiaGoc": 3733.33333333333, "trongSo": 0.8262946651689385, "dinhLuongDieuChinh": 12.394419977534078, "donGiaDieuChinh": 2986.666666666664}, {"name": "Trứng gà ta", "dinhLuongGoc": 25.0, "donGiaGoc": 7777.77777777778, "trongSo": 0.8253876467076572, "dinhLuongDieuChinh": 20.63469116769143, "donGiaDieuChinh": 6222.222222222224}]}], "Phụ sáng": [{"name": "Sữa chua probi", "weight": 1, "thanhPhanMonAn": [{"name": "Sữa chua Probi", "dinhLuongGoc": 65.0, "donGiaGoc": 4980.76923076923, "trongSo": 1.7802542948203892, "dinhLuongDieuChinh": 115.7165291633253, "donGiaDieuChinh": 3984.615384615384}]}], "Trưa": [{"name": "Cơm trắng", "weight": 0.6, "thanhPhanMonAn": [{"name": "Gạo tẻ máy", "dinhLuongGoc": 80.0, "donGiaGoc": 770.0, "trongSo": 0.7560607385561444, "dinhLuongDieuChinh": 60.48485908449155, "donGiaDieuChinh": 761.5558608334688}]}, {"name": "Thịt gà om nấm ", "weight": 0.2, "thanhPhanMonAn": [{"name": "Nấm hương khô", "dinhLuongGoc": 0.4, "donGiaGoc": 18550.0, "trongSo": 1.1916080662966957, "dinhLuongDieuChinh": 0.4766432265186783, "donGiaDieuChinh": 18550.0}, {"name": "Dầu thực vật", "dinhLuongGoc": 3.0, "donGiaGoc": 4270.0, "trongSo": 1.1916080662966957, "dinhLuongDieuChinh": 3.574824198890087, "donGiaDieuChinh": 4270.0}, {"name": "Gia vị", "dinhLuongGoc": 0.4, "donGiaGoc": 8750.0, "trongSo": 1.1916080662966957, "dinhLuongDieuChinh": 0.4766432265186783, "donGiaDieuChinh": 8750.0}, {"name": "Thịt gà công nghiệp, đùi(VDD)", "dinhLuongGoc": 60.0, "donGiaGoc": 7700.0, "trongSo": 1.1916080662966957, "dinhLuongDieuChinh": 71.49648397780174, "donGiaDieuChinh": 7700.0}]}, {"name": "Ngan om me khoai môn", "weight": 0.2, "thanhPhanMonAn": [{"name": "Khoai môn", "dinhLuongGoc": 20.0, "donGiaGoc": 1680.0, "trongSo": 0.21592561974754104, "dinhLuongDieuChinh": 4.318512394950821, "donGiaDieuChinh": 1680.0}, {"name": "Quả me chua", "dinhLuongGoc": 4.0, "donGiaGoc": 6650.0, "trongSo": 0.3833707192423582, "dinhLuongDieuChinh": 1.5334828769694329, "donGiaDieuChinh": 6650.0}, {"name": "Dầu thực vật", "dinhLuongGoc": 4.0, "donGiaGoc": 4270.0, "trongSo": 0.3833707192423582, "dinhLuongDieuChinh": 1.5334828769694329, "donGiaDieuChinh": 4270.0}, {"name": "Thịt ngan", "dinhLuongGoc": 40.0, "donGiaGoc": 8400.0, "trongSo": 0.4798661914505608, "dinhLuongDieuChinh": 19.194647658022433, "donGiaDieuChinh": 8400.0}, {"name": "Gia vị", "dinhLuongGoc": 0.4, "donGiaGoc": 8750.0, "trongSo": 0.5622942152031641, "dinhLuongDieuChinh": 0.22491768608126567, "donGiaDieuChinh": 8750.0}]}], "Chiều": [{"name": "Cháo cá lóc nấm rơm", "weight": 1, "thanhPhanMonAn": [{"name": "Gạo nếp cái", "dinhLuongGoc": 5.0, "donGiaGoc": 2800.0, "trongSo": 0.7977474133056175, "dinhLuongDieuChinh": 3.9887370665280875, "donGiaDieuChinh": 2800.0}, {"name": "Gạo tẻ máy", "dinhLuongGoc": 40.0, "donGiaGoc": 770.0, "trongSo": 0.813819728740304, "dinhLuongDieuChinh": 32.55278914961216, "donGiaDieuChinh": 770.0}, {"name": "Nấm rơm", "dinhLuongGoc": 15.0, "donGiaGoc": 5600.0, "trongSo": 0.8826574020874289, "dinhLuongDieuChinh": 13.239861031311435, "donGiaDieuChinh": 5600.0}, {"name": "Dầu thực vật", "dinhLuongGoc": 2.0, "donGiaGoc": 4270.0, "trongSo": 0.813819728740304, "dinhLuongDieuChinh": 1.627639457480608, "donGiaDieuChinh": 4270.0}, {"name": "Cá quả", "dinhLuongGoc": 30.0, "donGiaGoc": 7000.0, "trongSo": 0.813819728740304, "dinhLuongDieuChinh": 24.414591862209118, "donGiaDieuChinh": 7000.0}, {"name": "Gia vị", "dinhLuongGoc": 0.4, "donGiaGoc": 8750.0, "trongSo": 0.813819728740304, "dinhLuongDieuChinh": 0.3255278914961216, "donGiaDieuChinh": 8750.0}]}], "Phụ chiều": [{"name": "Chè đậu xanh nước cốt dừa", "weight": 1, "thanhPhanMonAn": [{"name": "Bột sắn dây", "dinhLuongGoc": 10.0, "donGiaGoc": 10500.0, "trongSo": 0.23810472663605722, "dinhLuongDieuChinh": 2.3810472663605724, "donGiaDieuChinh": 10500.0}, {"name": "Đậu xanh (đậu tắt)", "dinhLuongGoc": 35.0, "donGiaGoc": 2450.0, "trongSo": 0.38410080569790944, "dinhLuongDieuChinh": 13.443528199426831, "donGiaDieuChinh": 2450.0}, {"name": "Đường kính", "dinhLuongGoc": 8.0, "donGiaGoc": 1750.0, "trongSo": 0.31959549404003207, "dinhLuongDieuChinh": 2.5567639523202565, "donGiaDieuChinh": 1750.0}, {"name": "Nước cốt dừa", "dinhLuongGoc": 10.0, "donGiaGoc": 8750.0, "trongSo": 0.4779394172922062, "dinhLuongDieuChinh": 4.7793941729220615, "donGiaDieuChinh": 8750.0}]}]}, "type": 1, "result": ["Thành tiền: 21000.0 (OK)"],     "response": 200,
    "giaTien": 30000,
    "soBua": 5}