{"Menu": {"Sáng": [{"name": "Cháo bò cải thảo", "weight": 1, "thanhPhanMonAn": [{"name": "Gạo nếp cái", "dinhLuongGoc": 5.0, "donGiaGoc": 2800.0, "trongSo": 0.506169087180919, "dinhLuongDieuChinh": 2.5308454359045953, "donGiaDieuChinh": 2240.0}, {"name": "Gạo tẻ máy", "dinhLuongGoc": 40.0, "donGiaGoc": 770.0, "trongSo": 0.5202396965089251, "dinhLuongDieuChinh": 20.809587860357006, "donGiaDieuChinh": 616.0}, {"name": "Dầu thực vật", "dinhLuongGoc": 5.0, "donGiaGoc": 4270.0, "trongSo": 0.6409951980255373, "dinhLuongDieuChinh": 3.2049759901276866, "donGiaDieuChinh": 3416.0}, {"name": "Thịt bò loại I", "dinhLuongGoc": 30.0, "donGiaGoc": 17500.0, "trongSo": 0.506169087180919, "dinhLuongDieuChinh": 15.18507261542757, "donGiaDieuChinh": 14000.0}, {"name": "Gia vị", "dinhLuongGoc": 2.0, "donGiaGoc": 8750.0, "trongSo": 0.506169087180919, "dinhLuongDieuChinh": 1.012338174361838, "donGiaDieuChinh": 7000.0}, {"name": "Cải thảo", "dinhLuongGoc": 40.0, "donGiaGoc": 1750.0, "trongSo": 0.506169087180919, "dinhLuongDieuChinh": 20.246763487236763, "donGiaDieuChinh": 1400.0}]}], "Phụ sáng": [{"name": "Sữa chua Nutifood", "weight": 1, "thanhPhanMonAn": [{"name": "Sữa chua NutiFood", "dinhLuongGoc": 100.0, "donGiaGoc": 3500.0, "trongSo": 0.597880633322152, "dinhLuongDieuChinh": 59.7880633322152, "donGiaDieuChinh": 2800.0}]}], "Trưa": [{"name": "Cơm trắng", "weight": 0.6, "thanhPhanMonAn": [{"name": "Gạo tẻ máy", "dinhLuongGoc": 80.0, "donGiaGoc": 770.0, "trongSo": 0.8900292903217435, "dinhLuongDieuChinh": 71.20234322573948, "donGiaDieuChinh": 616.0}]}, {"name": "Thịt gà om nấm hương", "weight": 0.2, "thanhPhanMonAn": [{"name": "Nấm hương khô", "dinhLuongGoc": 5.0, "donGiaGoc": 18550.0, "trongSo": 0.6083793323701476, "dinhLuongDieuChinh": 3.041896661850738, "donGiaDieuChinh": 14840.0}, {"name": "Dầu thực vật", "dinhLuongGoc": 5.0, "donGiaGoc": 4270.0, "trongSo": 0.6083793323701476, "dinhLuongDieuChinh": 3.041896661850738, "donGiaDieuChinh": 3416.0}, {"name": "Gia vị", "dinhLuongGoc": 5.0, "donGiaGoc": 8750.0, "trongSo": 0.5681349071966146, "dinhLuongDieuChinh": 2.840674535983073, "donGiaDieuChinh": 7000.0}, {"name": "Nước mắm loại I", "dinhLuongGoc": 5.0, "donGiaGoc": 4666.66666666667, "trongSo": 0.5038173945788871, "dinhLuongDieuChinh": 2.5190869728944354, "donGiaDieuChinh": 3733.3333333333358}, {"name": "Thịt gà công nghiệp, đùi(VDD)", "dinhLuongGoc": 100.0, "donGiaGoc": 7700.0, "trongSo": 0.47679862182102295, "dinhLuongDieuChinh": 47.6798621821023, "donGiaDieuChinh": 6160.0}]}, {"name": "Canh su hào cà rốt", "weight": 0.2, "thanhPhanMonAn": [{"name": "Cà rốt (củ đỏ, vàng)", "dinhLuongGoc": 20.0, "donGiaGoc": 1400.0, "trongSo": 0.7313224837550074, "dinhLuongDieuChinh": 14.626449675100147, "donGiaDieuChinh": 1120.0}, {"name": "Hành lá", "dinhLuongGoc": 5.0, "donGiaGoc": 1260.0, "trongSo": 0.7313224837550074, "dinhLuongDieuChinh": 3.656612418775037, "donGiaDieuChinh": 1008.0}, {"name": "Su hào", "dinhLuongGoc": 35.0, "donGiaGoc": 3570.0, "trongSo": 0.6421432988388478, "dinhLuongDieuChinh": 22.475015459359675, "donGiaDieuChinh": 2856.0}, {"name": "Dầu thực vật", "dinhLuongGoc": 3.0, "donGiaGoc": 4270.0, "trongSo": 0.8844355445297198, "dinhLuongDieuChinh": 2.6533066335891595, "donGiaDieuChinh": 3416.0}, {"name": "Gia vị", "dinhLuongGoc": 0.4, "donGiaGoc": 8750.0, "trongSo": 0.7313224837550074, "dinhLuongDieuChinh": 0.29252899350200295, "donGiaDieuChinh": 7000.0}, {"name": "Xương cục", "dinhLuongGoc": 5.0, "donGiaGoc": 3850.0, "trongSo": 0.5730035570567458, "dinhLuongDieuChinh": 2.8650177852837286, "donGiaDieuChinh": 3080.0}]}], "Chiều": [{"name": "Bánh đa rau cải thịt", "weight": 1, "thanhPhanMonAn": [{"name": "Cải xanh", "dinhLuongGoc": 35.0, "donGiaGoc": 1750.0, "trongSo": 1.3679632986950259, "dinhLuongDieuChinh": 47.878715454325906, "donGiaDieuChinh": 1400.0}, {"name": "Dầu thực vật", "dinhLuongGoc": 3.0, "donGiaGoc": 4270.0, "trongSo": 1.3679632986950259, "dinhLuongDieuChinh": 4.103889896085078, "donGiaDieuChinh": 3416.0}, {"name": "Gia vị", "dinhLuongGoc": 0.4, "donGiaGoc": 8750.0, "trongSo": 1.3679632986950259, "dinhLuongDieuChinh": 0.5471853194780104, "donGiaDieuChinh": 7000.0}, {"name": "Thịt lợn, nạc vai", "dinhLuongGoc": 20.0, "donGiaGoc": 9566.66666666667, "trongSo": 1.2538424909666404, "dinhLuongDieuChinh": 25.076849819332807, "donGiaDieuChinh": 7653.333333333336}, {"name": "Bánh đa gạo", "dinhLuongGoc": 25.0, "donGiaGoc": 3080.0, "trongSo": 1.3679632986950259, "dinhLuongDieuChinh": 34.199082467375646, "donGiaDieuChinh": 2464.0}]}], "Phụ chiều": [{"name": "Sữa Etomilk 2", "weight": 1, "thanhPhanMonAn": [{"name": "Sữa bột Etomilk 2", "dinhLuongGoc": 30.0, "donGiaGoc": 40950.0, "trongSo": 0.8955460563468914, "dinhLuongDieuChinh": 26.866381690406744, "donGiaDieuChinh": 32760.0}]}]}, "type": 1, "result": ["Thành tiền: 22126.580680262003 (OK)"],     "response": 200,
    "giaTien": 30000,
    "soBua": 5}