{"Menu": {"Sáng": [{"name": "Súp thịt gà bí đỏ ngô ngọt", "weight": 1, "thanhPhanMonAn": [{"name": "Ngô bắp tươi", "dinhLuongGoc": 20.0, "donGiaGoc": 700.0, "trongSo": 0.6810932767582953, "dinhLuongDieuChinh": 13.621865535165906, "donGiaDieuChinh": 560.0}, {"name": "Bột sắn dây", "dinhLuongGoc": 15.0, "donGiaGoc": 10500.0, "trongSo": 0.6810932767582953, "dinhLuongDieuChinh": 10.21639915137443, "donGiaDieuChinh": 8400.0}, {"name": "Bí ngô", "dinhLuongGoc": 15.0, "donGiaGoc": 2800.0, "trongSo": 0.6810932767582953, "dinhLuongDieuChinh": 10.21639915137443, "donGiaDieuChinh": 2240.0}, {"name": "Trứng gà ta", "dinhLuongGoc": 5.0, "donGiaGoc": 7777.77777777778, "trongSo": 0.6810932767582953, "dinhLuongDieuChinh": 3.4054663837914765, "donGiaDieuChinh": 6222.222222222224}, {"name": "Thịt gà công nghiệp, đùi(VDD)", "dinhLuongGoc": 15.0, "donGiaGoc": 7700.0, "trongSo": 0.6810932767582953, "dinhLuongDieuChinh": 10.21639915137443, "donGiaDieuChinh": 6160.0}]}], "Phụ sáng": [{"name": "Sữa đậu xanh hạt sen", "weight": 1, "thanhPhanMonAn": [{"name": "Đậu xanh (đậu tắt)", "dinhLuongGoc": 10.0, "donGiaGoc": 2450.0, "trongSo": 0.27673140630181603, "dinhLuongDieuChinh": 2.7673140630181603, "donGiaDieuChinh": 1960.0}, {"name": "Hạt sen khô", "dinhLuongGoc": 10.0, "donGiaGoc": 17500.0, "trongSo": 0.27673140630181603, "dinhLuongDieuChinh": 2.7673140630181603, "donGiaDieuChinh": 14000.0}, {"name": "Sữa đặc có đường Việt Nam", "dinhLuongGoc": 10.0, "donGiaGoc": 5526.31578947368, "trongSo": 0.27673140630181603, "dinhLuongDieuChinh": 2.7673140630181603, "donGiaDieuChinh": 4421.052631578944}, {"name": "Đường kính", "dinhLuongGoc": 10.0, "donGiaGoc": 1750.0, "trongSo": 0.27673140630181603, "dinhLuongDieuChinh": 2.7673140630181603, "donGiaDieuChinh": 1400.0}]}], "Trưa": [{"name": "Cơm gạo tám", "weight": 0.6, "thanhPhanMonAn": [{"name": "Gạo tám", "dinhLuongGoc": 80.0, "donGiaGoc": 1750.0, "trongSo": 0.8261795932894742, "dinhLuongDieuChinh": 66.09436746315794, "donGiaDieuChinh": 1400.0}]}, {"name": "Thịt lợn sốt cà chua", "weight": 0.2, "thanhPhanMonAn": [{"name": "Cà chua", "dinhLuongGoc": 30.0, "donGiaGoc": 840.0, "trongSo": 1.1360243785513688, "dinhLuongDieuChinh": 34.080731356541065, "donGiaDieuChinh": 672.0}, {"name": "Dầu thực vật", "dinhLuongGoc": 2.0, "donGiaGoc": 4270.0, "trongSo": 1.1360243785513688, "dinhLuongDieuChinh": 2.2720487571027377, "donGiaDieuChinh": 3416.0}, {"name": "Thịt lợn nạc", "dinhLuongGoc": 30.0, "donGiaGoc": 9566.66666666667, "trongSo": 1.1360243785513688, "dinhLuongDieuChinh": 34.080731356541065, "donGiaDieuChinh": 7653.333333333336}, {"name": "Gia vị", "dinhLuongGoc": 0.4, "donGiaGoc": 8750.0, "trongSo": 1.1360243785513688, "dinhLuongDieuChinh": 0.45440975142054757, "donGiaDieuChinh": 7000.0}]}, {"name": "Đậu trạch xào thịt bò", "weight": 0.2, "thanhPhanMonAn": [{"name": "Đậu cô ve", "dinhLuongGoc": 20.0, "donGiaGoc": 1400.0, "trongSo": 1.8184117421610306, "dinhLuongDieuChinh": 36.36823484322061, "donGiaDieuChinh": 1120.0}, {"name": "Tỏi ta", "dinhLuongGoc": 8.0, "donGiaGoc": 1540.0, "trongSo": 1.8184117421610306, "dinhLuongDieuChinh": 14.547293937288245, "donGiaDieuChinh": 1232.0}, {"name": "Thịt bò loại I", "dinhLuongGoc": 15.0, "donGiaGoc": 17500.0, "trongSo": 1.8184117421610306, "dinhLuongDieuChinh": 27.276176132415458, "donGiaDieuChinh": 14000.0}]}], "Chiều": [{"name": "Mỳ chũ nấu tôm thịt băm", "weight": 1, "thanhPhanMonAn": [{"name": "Hành lá", "dinhLuongGoc": 5.0, "donGiaGoc": 1260.0, "trongSo": 1.4608062513240068, "dinhLuongDieuChinh": 7.304031256620034, "donGiaDieuChinh": 1008.0}, {"name": "Dầu thực vật", "dinhLuongGoc": 2.0, "donGiaGoc": 4270.0, "trongSo": 1.4608062513240068, "dinhLuongDieuChinh": 2.9216125026480135, "donGiaDieuChinh": 3416.0}, {"name": "Tôm lớp", "dinhLuongGoc": 10.0, "donGiaGoc": 12600.0, "trongSo": 1.4608062513240068, "dinhLuongDieuChinh": 14.608062513240068, "donGiaDieuChinh": 10080.0}, {"name": "Gia vị", "dinhLuongGoc": 0.4, "donGiaGoc": 8750.0, "trongSo": 1.4608062513240068, "dinhLuongDieuChinh": 0.5843225005296028, "donGiaDieuChinh": 7000.0}, {"name": "Thịt lợn, nạc vai", "dinhLuongGoc": 20.0, "donGiaGoc": 9566.66666666667, "trongSo": 1.4608062513240068, "dinhLuongDieuChinh": 29.216125026480135, "donGiaDieuChinh": 7653.333333333336}, {"name": "Bánh đa gạo", "dinhLuongGoc": 40.0, "donGiaGoc": 3080.0, "trongSo": 1.4608062513240068, "dinhLuongDieuChinh": 58.43225005296027, "donGiaDieuChinh": 2464.0}]}], "Phụ chiều": [{"name": "Váng sữa monte", "weight": 1, "thanhPhanMonAn": [{"name": "Váng sữa monte", "dinhLuongGoc": 55.0, "donGiaGoc": 20522.7272727273, "trongSo": 1.1750855149589852, "dinhLuongDieuChinh": 64.62970332274418, "donGiaDieuChinh": 16418.18181818184}]}]}, "type": 1, "result": ["Thành tiền: 26858.194844936686 (OK)"],     "response": 200,
    "giaTien": 30000,
    "soBua": 5}