{"Menu": {"Sáng": [{"name": "Súp thịt bò bí đỏ", "weight": 1, "thanhPhanMonAn": [{"name": "Bí ngô", "dinhLuongGoc": 15.0, "donGiaGoc": 2800.0, "trongSo": 1.0, "dinhLuongDieuChinh": 15.0, "donGiaDieuChinh": 3360.0}, {"name": "Rau mùi", "dinhLuongGoc": 10.0, "donGiaGoc": 2800.0, "trongSo": 1.0, "dinhLuongDieuChinh": 10.0, "donGiaDieuChinh": 3360.0}, {"name": "Dầu thực vật", "dinhLuongGoc": 3.0, "donGiaGoc": 4270.0, "trongSo": 1.0, "dinhLuongDieuChinh": 3.0, "donGiaDieuChinh": 5124.0}, {"name": "Thịt bò loại I", "dinhLuongGoc": 20.0, "donGiaGoc": 17500.0, "trongSo": 1.0, "dinhLuongDieuChinh": 20.0, "donGiaDieuChinh": 21000.0}, {"name": "Gia vị", "dinhLuongGoc": 2.0, "donGiaGoc": 8750.0, "trongSo": 1.0, "dinhLuongDieuChinh": 2.0, "donGiaDieuChinh": 10500.0}, {"name": "Bột ngô + bột năng", "dinhLuongGoc": 15.0, "donGiaGoc": 3733.33333333333, "trongSo": 0.9002956415946134, "dinhLuongDieuChinh": 13.5044346239192, "donGiaDieuChinh": 4479.999999999996}]}], "Phụ sáng": [{"name": "Nước nhãn nhục", "weight": 1, "thanhPhanMonAn": [{"name": "Hạt sen khô", "dinhLuongGoc": 3.0, "donGiaGoc": 17500.0, "trongSo": 1.0639329494198633, "dinhLuongDieuChinh": 3.19179884825959, "donGiaDieuChinh": 21000.0}, {"name": "Nhãn khô", "dinhLuongGoc": 5.0, "donGiaGoc": 16800.0, "trongSo": 1.0, "dinhLuongDieuChinh": 5.0, "donGiaDieuChinh": 20160.0}, {"name": "Đường kính", "dinhLuongGoc": 3.0, "donGiaGoc": 1750.0, "trongSo": 0.999006880717238, "dinhLuongDieuChinh": 2.997020642151714, "donGiaDieuChinh": 2100.0}, {"name": "Nước dừa non tươi", "dinhLuongGoc": 30.0, "donGiaGoc": 2100.0, "trongSo": 1.0, "dinhLuongDieuChinh": 30.0, "donGiaDieuChinh": 2520.0}]}], "Trưa": [{"name": "Cơm gạo tám", "weight": 0.6, "thanhPhanMonAn": [{"name": "Gạo tám", "dinhLuongGoc": 80.0, "donGiaGoc": 1750.0, "trongSo": 0.8144668780898594, "dinhLuongDieuChinh": 65.15735024718876, "donGiaDieuChinh": 2100.0}]}, {"name": "Thịt, đậu sốt cà chua", "weight": 0.2, "thanhPhanMonAn": [{"name": "Đậu phụ", "dinhLuongGoc": 25.0, "donGiaGoc": 2800.0, "trongSo": 0.6543602428177908, "dinhLuongDieuChinh": 16.35900607044477, "donGiaDieuChinh": 3360.0}, {"name": "Cà chua", "dinhLuongGoc": 20.0, "donGiaGoc": 840.0, "trongSo": 0.5270112484984446, "dinhLuongDieuChinh": 10.540224969968893, "donGiaDieuChinh": 1008.0}, {"name": "Hành lá", "dinhLuongGoc": 5.0, "donGiaGoc": 1260.0, "trongSo": 0.5270112484984446, "dinhLuongDieuChinh": 2.6350562424922233, "donGiaDieuChinh": 1512.0}, {"name": "Dầu thực vật", "dinhLuongGoc": 5.0, "donGiaGoc": 4270.0, "trongSo": 0.5746940803532608, "dinhLuongDieuChinh": 2.873470401766304, "donGiaDieuChinh": 5124.0}, {"name": "Gia vị", "dinhLuongGoc": 0.4, "donGiaGoc": 8750.0, "trongSo": 0.4445211640097495, "dinhLuongDieuChinh": 0.17780846560389982, "donGiaDieuChinh": 10500.0}, {"name": "Thịt lợn, nạc vai", "dinhLuongGoc": 35.0, "donGiaGoc": 9566.66666666667, "trongSo": 0.6848064266978442, "dinhLuongDieuChinh": 23.968224934424548, "donGiaDieuChinh": 11480.000000000004}]}, {"name": "Khoai tây chiên", "weight": 0.2, "thanhPhanMonAn": [{"name": "Khoai tây", "dinhLuongGoc": 50.0, "donGiaGoc": 1750.0, "trongSo": 0.677834408931984, "dinhLuongDieuChinh": 33.8917204465992, "donGiaDieuChinh": 2100.0}, {"name": "Bột chiên giòn", "dinhLuongGoc": 10.0, "donGiaGoc": 4200.0, "trongSo": 0.7139785810441648, "dinhLuongDieuChinh": 7.139785810441648, "donGiaDieuChinh": 5040.0}, {"name": "Dầu ăn Meizan (Kg)", "dinhLuongGoc": 5.0, "donGiaGoc": 3150.0, "trongSo": 0.8836926800535567, "dinhLuongDieuChinh": 4.418463400267783, "donGiaDieuChinh": 3780.0}, {"name": "Bột canh Hải Châu", "dinhLuongGoc": 3.0, "donGiaGoc": 1473.68421052632, "trongSo": 0.8577525221021203, "dinhLuongDieuChinh": 2.573257566306361, "donGiaDieuChinh": 1768.421052631584}]}], "Chiều": [{"name": "Cháo thịt rau xanh", "weight": 1, "thanhPhanMonAn": [{"name": "Gạo nếp cái", "dinhLuongGoc": 5.0, "donGiaGoc": 2800.0, "trongSo": 0.5545208556876887, "dinhLuongDieuChinh": 2.7726042784384437, "donGiaDieuChinh": 3101.1232612776626}, {"name": "Gạo tẻ máy", "dinhLuongGoc": 40.0, "donGiaGoc": 770.0, "trongSo": 0.3652532946107751, "dinhLuongDieuChinh": 14.610131784431005, "donGiaDieuChinh": 770.0}, {"name": "Cải xanh", "dinhLuongGoc": 40.0, "donGiaGoc": 1750.0, "trongSo": 0.5545208556876887, "dinhLuongDieuChinh": 22.18083422750755, "donGiaDieuChinh": 1750.0}, {"name": "Dầu thực vật", "dinhLuongGoc": 5.0, "donGiaGoc": 4270.0, "trongSo": 0.6251802013520498, "dinhLuongDieuChinh": 3.125901006760249, "donGiaDieuChinh": 4270.0}, {"name": "Gia vị", "dinhLuongGoc": 2.0, "donGiaGoc": 8750.0, "trongSo": 0.4522526428721494, "dinhLuongDieuChinh": 0.9045052857442988, "donGiaDieuChinh": 8750.0}, {"name": "Thịt lợn, nạc vai", "dinhLuongGoc": 40.0, "donGiaGoc": 9566.66666666667, "trongSo": 0.6664625786249936, "dinhLuongDieuChinh": 26.65850314499974, "donGiaDieuChinh": 9566.66666666667}]}], "Phụ chiều": [{"name": "Chuối tây", "weight": 1, "thanhPhanMonAn": [{"name": "Chuối tây", "dinhLuongGoc": 70.0, "donGiaGoc": 2100.0, "trongSo": 1.958410092724236, "dinhLuongDieuChinh": 137.08870649069652, "donGiaDieuChinh": 2100.0}]}]}, "type": 1, "result": ["Thành tiền: 21000.0 (OK)"],     "response": 200,
    "giaTien": 30000,
    "soBua": 5}