{"Menu": {"Sáng": [{"name": "Cháo gà nấm hương", "weight": 1, "thanhPhanMonAn": [{"name": "Gạo nếp cái", "dinhLuongGoc": 5.0, "donGiaGoc": 2800.0, "trongSo": 0.2742803248835125, "dinhLuongDieuChinh": 1.3714016244175626, "donGiaDieuChinh": 2240.0}, {"name": "Gạo tẻ máy", "dinhLuongGoc": 40.0, "donGiaGoc": 770.0, "trongSo": 0.2742803248835125, "dinhLuongDieuChinh": 10.971212995340501, "donGiaDieuChinh": 616.0}, {"name": "Hành lá", "dinhLuongGoc": 3.0, "donGiaGoc": 1260.0, "trongSo": 0.2742803248835125, "dinhLuongDieuChinh": 0.8228409746505375, "donGiaDieuChinh": 1008.0}, {"name": "Nấm hương khô", "dinhLuongGoc": 0.5, "donGiaGoc": 18550.0, "trongSo": 0.2742803248835125, "dinhLuongDieuChinh": 0.13714016244175625, "donGiaDieuChinh": 14840.0}, {"name": "Dầu thực vật", "dinhLuongGoc": 5.0, "donGiaGoc": 4270.0, "trongSo": 0.2742803248835125, "dinhLuongDieuChinh": 1.3714016244175626, "donGiaDieuChinh": 3416.0}, {"name": "Gia vị", "dinhLuongGoc": 2.0, "donGiaGoc": 8750.0, "trongSo": 0.2742803248835125, "dinhLuongDieuChinh": 0.548560649767025, "donGiaDieuChinh": 7000.0}, {"name": "Thịt gà công nghiệp, đùi(VDD)", "dinhLuongGoc": 30.0, "donGiaGoc": 7700.0, "trongSo": 0.2742803248835125, "dinhLuongDieuChinh": 8.228409746505376, "donGiaDieuChinh": 6160.0}]}], "Phụ sáng": [{"name": "Sữa netsure grow", "weight": 1, "thanhPhanMonAn": [{"name": "Sữa netsure grow", "dinhLuongGoc": 18.0, "donGiaGoc": 18666.6666666667, "trongSo": 3.5410727593089257, "dinhLuongDieuChinh": 63.73930966756066, "donGiaDieuChinh": 14933.333333333361}]}], "Trưa": [{"name": "Cơm gạo tám", "weight": 0.6, "thanhPhanMonAn": [{"name": "Gạo tám", "dinhLuongGoc": 80.0, "donGiaGoc": 1750.0, "trongSo": 0.8382544435327175, "dinhLuongDieuChinh": 67.0603554826174, "donGiaDieuChinh": 1400.0}]}, {"name": "Thịt lợn om nấm", "weight": 0.2, "thanhPhanMonAn": [{"name": "Nấm hương khô", "dinhLuongGoc": 0.4, "donGiaGoc": 18550.0, "trongSo": 2.537841314705778, "dinhLuongDieuChinh": 1.0151365258823113, "donGiaDieuChinh": 14840.0}, {"name": "Dầu thực vật", "dinhLuongGoc": 2.0, "donGiaGoc": 4270.0, "trongSo": 2.537841314705778, "dinhLuongDieuChinh": 5.075682629411556, "donGiaDieuChinh": 3416.0}, {"name": "Thịt lợn nạc", "dinhLuongGoc": 25.0, "donGiaGoc": 9566.66666666667, "trongSo": 2.537841314705778, "dinhLuongDieuChinh": 63.446032867644455, "donGiaDieuChinh": 7653.333333333336}, {"name": "Gia vị", "dinhLuongGoc": 0.4, "donGiaGoc": 8750.0, "trongSo": 2.537841314705778, "dinhLuongDieuChinh": 1.0151365258823113, "donGiaDieuChinh": 7000.0}]}, {"name": "Củ cải luộc chấm muối vừng", "weight": 0.2, "thanhPhanMonAn": [{"name": "Lạc hạt", "dinhLuongGoc": 20.0, "donGiaGoc": 5250.0, "trongSo": 0.5371336641213916, "dinhLuongDieuChinh": 10.742673282427832, "donGiaDieuChinh": 4200.0}, {"name": "Vừng (đen, trắng)", "dinhLuongGoc": 4.0, "donGiaGoc": 7000.0, "trongSo": 0.5371336641213916, "dinhLuongDieuChinh": 2.1485346564855665, "donGiaDieuChinh": 5600.0}, {"name": "Củ cải trắng", "dinhLuongGoc": 45.0, "donGiaGoc": 2100.0, "trongSo": 0.5371336641213916, "dinhLuongDieuChinh": 24.171014885462622, "donGiaDieuChinh": 1680.0}, {"name": "Gia vị", "dinhLuongGoc": 2.0, "donGiaGoc": 8750.0, "trongSo": 0.5371336641213916, "dinhLuongDieuChinh": 1.0742673282427833, "donGiaDieuChinh": 7000.0}]}], "Chiều": [{"name": "Mỳ thịt lợn", "weight": 1, "thanhPhanMonAn": [{"name": "Mỳ sợi", "dinhLuongGoc": 80.0, "donGiaGoc": 2240.0, "trongSo": 0.5520252085951874, "dinhLuongDieuChinh": 44.162016687614994, "donGiaDieuChinh": 1792.0}, {"name": "Dầu thực vật", "dinhLuongGoc": 2.0, "donGiaGoc": 4270.0, "trongSo": 0.5520252085951874, "dinhLuongDieuChinh": 1.1040504171903749, "donGiaDieuChinh": 3416.0}, {"name": "Thịt lợn nạc", "dinhLuongGoc": 30.0, "donGiaGoc": 9566.66666666667, "trongSo": 0.5520252085951874, "dinhLuongDieuChinh": 16.560756257855623, "donGiaDieuChinh": 7653.333333333336}, {"name": "Gia vị", "dinhLuongGoc": 0.4, "donGiaGoc": 8750.0, "trongSo": 0.5520252085951874, "dinhLuongDieuChinh": 0.22081008343807498, "donGiaDieuChinh": 7000.0}]}], "Phụ chiều": [{"name": "Táo Mỹ", "weight": 1, "thanhPhanMonAn": [{"name": "Táo tây", "dinhLuongGoc": 50.0, "donGiaGoc": 5320.0, "trongSo": 3.1212062553090116, "dinhLuongDieuChinh": 156.0603127654506, "donGiaDieuChinh": 4256.0}]}]}, "type": 1, "result": ["Thành tiền: 26233.85352176112 (OK)"],     "response": 200,
    "giaTien": 30000,
    "soBua": 5}