{"Menu": {"Sáng": [{"name": "Cháo bò hành thơm", "weight": 1, "thanhPhanMonAn": [{"name": "Gạo nếp cái", "dinhLuongGoc": 5.0, "donGiaGoc": 2800.0, "trongSo": 0.35185995490068267, "dinhLuongDieuChinh": 1.7592997745034133, "donGiaDieuChinh": 2240.0}, {"name": "Gạo tẻ máy", "dinhLuongGoc": 40.0, "donGiaGoc": 770.0, "trongSo": 0.35185995490068267, "dinhLuongDieuChinh": 14.074398196027307, "donGiaDieuChinh": 616.0}, {"name": "Hành lá", "dinhLuongGoc": 3.0, "donGiaGoc": 1260.0, "trongSo": 0.35185995490068267, "dinhLuongDieuChinh": 1.055579864702048, "donGiaDieuChinh": 1008.0}, {"name": "Rau mùi", "dinhLuongGoc": 3.0, "donGiaGoc": 2800.0, "trongSo": 0.35185995490068267, "dinhLuongDieuChinh": 1.055579864702048, "donGiaDieuChinh": 2240.0}, {"name": "Dầu thực vật", "dinhLuongGoc": 5.0, "donGiaGoc": 4270.0, "trongSo": 0.35185995490068267, "dinhLuongDieuChinh": 1.7592997745034133, "donGiaDieuChinh": 3416.0}, {"name": "Thịt bò loại I", "dinhLuongGoc": 25.0, "donGiaGoc": 17500.0, "trongSo": 0.35185995490068267, "dinhLuongDieuChinh": 8.796498872517066, "donGiaDieuChinh": 14000.0}, {"name": "Gia vị", "dinhLuongGoc": 0.3, "donGiaGoc": 8750.0, "trongSo": 0.35185995490068267, "dinhLuongDieuChinh": 0.1055579864702048, "donGiaDieuChinh": 7000.0}]}], "Phụ sáng": [{"name": "Chè đậu xanh nước cốt dừa", "weight": 1, "thanhPhanMonAn": [{"name": "Bột sắn dây", "dinhLuongGoc": 10.0, "donGiaGoc": 10500.0, "trongSo": 0.19474987437239347, "dinhLuongDieuChinh": 1.9474987437239346, "donGiaDieuChinh": 8400.0}, {"name": "Đậu xanh (đậu tắt)", "dinhLuongGoc": 35.0, "donGiaGoc": 2450.0, "trongSo": 0.19474987437239347, "dinhLuongDieuChinh": 6.816245603033772, "donGiaDieuChinh": 1960.0}, {"name": "Đường kính", "dinhLuongGoc": 8.0, "donGiaGoc": 1750.0, "trongSo": 0.19474987437239347, "dinhLuongDieuChinh": 1.5579989949791477, "donGiaDieuChinh": 1400.0}, {"name": "Nước cốt dừa", "dinhLuongGoc": 10.0, "donGiaGoc": 8750.0, "trongSo": 0.19474987437239347, "dinhLuongDieuChinh": 1.9474987437239346, "donGiaDieuChinh": 7000.0}]}], "Trưa": [{"name": "Cơm trắng", "weight": 0.6, "thanhPhanMonAn": [{"name": "Gạo tẻ máy", "dinhLuongGoc": 80.0, "donGiaGoc": 770.0, "trongSo": 0.9964346194608519, "dinhLuongDieuChinh": 79.71476955686815, "donGiaDieuChinh": 616.0}]}, {"name": "Cà ri gà", "weight": 0.2, "thanhPhanMonAn": [{"name": "Khoai tây", "dinhLuongGoc": 35.0, "donGiaGoc": 1750.0, "trongSo": 0.6107592496605311, "dinhLuongDieuChinh": 21.376573738118587, "donGiaDieuChinh": 1400.0}, {"name": "Cà rốt (củ đỏ, vàng)", "dinhLuongGoc": 30.0, "donGiaGoc": 1400.0, "trongSo": 0.6107592496605311, "dinhLuongDieuChinh": 18.322777489815934, "donGiaDieuChinh": 1120.0}, {"name": "Hành lá", "dinhLuongGoc": 3.0, "donGiaGoc": 1260.0, "trongSo": 0.6107592496605311, "dinhLuongDieuChinh": 1.8322777489815931, "donGiaDieuChinh": 1008.0}, {"name": "Dầu thực vật", "dinhLuongGoc": 5.0, "donGiaGoc": 4270.0, "trongSo": 0.6107592496605311, "dinhLuongDieuChinh": 3.0537962483026555, "donGiaDieuChinh": 3416.0}, {"name": "Cary bột", "dinhLuongGoc": 10.0, "donGiaGoc": 32200.0, "trongSo": 0.6107592496605311, "dinhLuongDieuChinh": 6.107592496605311, "donGiaDieuChinh": 25760.0}, {"name": "Gia vị", "dinhLuongGoc": 0.4, "donGiaGoc": 8750.0, "trongSo": 0.6107592496605311, "dinhLuongDieuChinh": 0.24430369986421244, "donGiaDieuChinh": 7000.0}, {"name": "Thịt gà công nghiệp, đùi(VDD)", "dinhLuongGoc": 40.0, "donGiaGoc": 7700.0, "trongSo": 0.6107592496605311, "dinhLuongDieuChinh": 24.430369986421244, "donGiaDieuChinh": 6160.0}]}, {"name": "Canh bí đỏ thịt bò băm", "weight": 0.2, "thanhPhanMonAn": [{"name": "Bí ngô", "dinhLuongGoc": 35.0, "donGiaGoc": 2800.0, "trongSo": 1.1680894049460906, "dinhLuongDieuChinh": 40.88312917311317, "donGiaDieuChinh": 2240.0}, {"name": "Tỏi ta", "dinhLuongGoc": 1.0, "donGiaGoc": 1540.0, "trongSo": 1.1680894049460906, "dinhLuongDieuChinh": 1.1680894049460906, "donGiaDieuChinh": 1232.0}, {"name": "Dầu thực vật", "dinhLuongGoc": 4.0, "donGiaGoc": 4270.0, "trongSo": 1.1680894049460906, "dinhLuongDieuChinh": 4.672357619784362, "donGiaDieuChinh": 3416.0}, {"name": "Thịt bò loại I", "dinhLuongGoc": 20.0, "donGiaGoc": 17500.0, "trongSo": 1.1680894049460906, "dinhLuongDieuChinh": 23.361788098921814, "donGiaDieuChinh": 17356.224207260693}, {"name": "Gia vị", "dinhLuongGoc": 1.0, "donGiaGoc": 8750.0, "trongSo": 1.1680894049460906, "dinhLuongDieuChinh": 1.1680894049460906, "donGiaDieuChinh": 8750.000000000311}]}], "Chiều": [{"name": "Súp thịt bơ bí đỏ nấm hương", "weight": 1, "thanhPhanMonAn": [{"name": "Bí ngô", "dinhLuongGoc": 25.0, "donGiaGoc": 2800.0, "trongSo": 1.0, "dinhLuongDieuChinh": 25.0, "donGiaDieuChinh": 2800.0}, {"name": "Nấm hương khô", "dinhLuongGoc": 10.0, "donGiaGoc": 18550.0, "trongSo": 1.0, "dinhLuongDieuChinh": 10.0, "donGiaDieuChinh": 18550.0}, {"name": "Bơ", "dinhLuongGoc": 5.0, "donGiaGoc": 13039.2156862745, "trongSo": 1.0, "dinhLuongDieuChinh": 5.0, "donGiaDieuChinh": 13039.2156862745}, {"name": "Thịt lợn, nạc vai", "dinhLuongGoc": 25.0, "donGiaGoc": 9566.66666666667, "trongSo": 1.0, "dinhLuongDieuChinh": 25.0, "donGiaDieuChinh": 9566.66666666667}, {"name": "Bột ngô + bột năng", "dinhLuongGoc": 15.0, "donGiaGoc": 3733.33333333333, "trongSo": 1.0, "dinhLuongDieuChinh": 15.0, "donGiaDieuChinh": 3733.33333333333}]}], "Phụ chiều": [{"name": "Sữa kê hạt sen", "weight": 1, "thanhPhanMonAn": [{"name": "Kê", "dinhLuongGoc": 15.0, "donGiaGoc": 21000.0, "trongSo": 0.6355326593905849, "dinhLuongDieuChinh": 9.532989890858774, "donGiaDieuChinh": 21000.0}, {"name": "Hạt sen khô", "dinhLuongGoc": 10.0, "donGiaGoc": 17500.0, "trongSo": 0.6355326593905849, "dinhLuongDieuChinh": 6.355326593905849, "donGiaDieuChinh": 17500.0}, {"name": "Đường kính", "dinhLuongGoc": 5.0, "donGiaGoc": 1750.0, "trongSo": 0.6355326593905849, "dinhLuongDieuChinh": 3.1776632969529244, "donGiaDieuChinh": 1750.0}, {"name": "Sữa đặc Vinamilk", "dinhLuongGoc": 8.0, "donGiaGoc": 5833.33333333333, "trongSo": 0.6355326593905849, "dinhLuongDieuChinh": 5.084261275124679, "donGiaDieuChinh": 5833.33333333333}]}]}, "type": 1, "result": ["Thành tiền: 21000.0 (OK)"],     "response": 200,
    "giaTien": 30000,
    "soBua": 5}